{"format": "graph-model", "generatedBy": "2.11.0", "convertedBy": "TensorFlow.js Converter v4.2.0", "signature": {"inputs": {"tcat:0": {"name": "tcat:0", "dtype": "DT_FLOAT", "tensorShape": {"dim": [{"size": "-1"}]}}, "acgt:0": {"name": "acgt:0", "dtype": "DT_FLOAT", "tensorShape": {"dim": [{"size": "-1"}]}}, "ttca:0": {"name": "ttca:0", "dtype": "DT_FLOAT", "tensorShape": {"dim": [{"size": "-1"}]}}, "gctc:0": {"name": "gctc:0", "dtype": "DT_FLOAT", "tensorShape": {"dim": [{"size": "-1"}]}}, "acga:0": {"name": "acga:0", "dtype": "DT_FLOAT", "tensorShape": {"dim": [{"size": "-1"}]}}, "ttag:0": {"name": "ttag:0", "dtype": "DT_FLOAT", "tensorShape": {"dim": [{"size": "-1"}]}}, "tctc:0": {"name": "tctc:0", "dtype": "DT_FLOAT", "tensorShape": {"dim": [{"size": "-1"}]}}, "gtcc:0": {"name": "gtcc:0", "dtype": "DT_FLOAT", "tensorShape": {"dim": [{"size": "-1"}]}}, "ttga:0": {"name": "ttga:0", "dtype": "DT_FLOAT", "tensorShape": {"dim": [{"size": "-1"}]}}, "actt:0": {"name": "actt:0", "dtype": "DT_FLOAT", "tensorShape": {"dim": [{"size": "-1"}]}}, "ttat:0": {"name": "ttat:0", "dtype": "DT_FLOAT", "tensorShape": {"dim": [{"size": "-1"}]}}, "acta:0": {"name": "acta:0", "dtype": "DT_FLOAT", "tensorShape": {"dim": [{"size": "-1"}]}}, "gcga:0": {"name": "gcga:0", "dtype": "DT_FLOAT", "tensorShape": {"dim": [{"size": "-1"}]}}, "ttgg:0": {"name": "ttgg:0", "dtype": "DT_FLOAT", "tensorShape": {"dim": [{"size": "-1"}]}}, "acgg:0": {"name": "acgg:0", "dtype": "DT_FLOAT", "tensorShape": {"dim": [{"size": "-1"}]}}, "ctgc:0": {"name": "ctgc:0", "dtype": "DT_FLOAT", "tensorShape": {"dim": [{"size": "-1"}]}}, "gtca:0": {"name": "gtca:0", "dtype": "DT_FLOAT", "tensorShape": {"dim": [{"size": "-1"}]}}, "gtct:0": {"name": "gtct:0", "dtype": "DT_FLOAT", "tensorShape": {"dim": [{"size": "-1"}]}}, "actc:0": {"name": "actc:0", "dtype": "DT_FLOAT", "tensorShape": {"dim": [{"size": "-1"}]}}, "gcgt:0": {"name": "gcgt:0", "dtype": "DT_FLOAT", "tensorShape": {"dim": [{"size": "-1"}]}}, "ccgc:0": {"name": "ccgc:0", "dtype": "DT_FLOAT", "tensorShape": {"dim": [{"size": "-1"}]}}, "atcg:0": {"name": "atcg:0", "dtype": "DT_FLOAT", "tensorShape": {"dim": [{"size": "-1"}]}}, "gtat:0": {"name": "gtat:0", "dtype": "DT_FLOAT", "tensorShape": {"dim": [{"size": "-1"}]}}, "gcgg:0": {"name": "gcgg:0", "dtype": "DT_FLOAT", "tensorShape": {"dim": [{"size": "-1"}]}}, "ttct:0": {"name": "ttct:0", "dtype": "DT_FLOAT", "tensorShape": {"dim": [{"size": "-1"}]}}, "tcaa:0": {"name": "tcaa:0", "dtype": "DT_FLOAT", "tensorShape": {"dim": [{"size": "-1"}]}}, "gtga:0": {"name": "gtga:0", "dtype": "DT_FLOAT", "tensorShape": {"dim": [{"size": "-1"}]}}, "tcac:0": {"name": "tcac:0", "dtype": "DT_FLOAT", "tensorShape": {"dim": [{"size": "-1"}]}}, "acag:0": {"name": "acag:0", "dtype": "DT_FLOAT", "tensorShape": {"dim": [{"size": "-1"}]}}, "gtaa:0": {"name": "gtaa:0", "dtype": "DT_FLOAT", "tensorShape": {"dim": [{"size": "-1"}]}}, "ctaa:0": {"name": "ctaa:0", "dtype": "DT_FLOAT", "tensorShape": {"dim": [{"size": "-1"}]}}, "unknown:0": {"name": "unknown:0", "dtype": "DT_RESOURCE", "tensorShape": {}, "resourceId": 2726}, "ttcg:0": {"name": "ttcg:0", "dtype": "DT_FLOAT", "tensorShape": {"dim": [{"size": "-1"}]}}, "ctca:0": {"name": "ctca:0", "dtype": "DT_FLOAT", "tensorShape": {"dim": [{"size": "-1"}]}}, "gtgc:0": {"name": "gtgc:0", "dtype": "DT_FLOAT", "tensorShape": {"dim": [{"size": "-1"}]}}, "atac:0": {"name": "atac:0", "dtype": "DT_FLOAT", "tensorShape": {"dim": [{"size": "-1"}]}}, "ttac:0": {"name": "ttac:0", "dtype": "DT_FLOAT", "tensorShape": {"dim": [{"size": "-1"}]}}, "ctga:0": {"name": "ctga:0", "dtype": "DT_FLOAT", "tensorShape": {"dim": [{"size": "-1"}]}}, "ccag:0": {"name": "ccag:0", "dtype": "DT_FLOAT", "tensorShape": {"dim": [{"size": "-1"}]}}, "atgg:0": {"name": "atgg:0", "dtype": "DT_FLOAT", "tensorShape": {"dim": [{"size": "-1"}]}}, "gtag:0": {"name": "gtag:0", "dtype": "DT_FLOAT", "tensorShape": {"dim": [{"size": "-1"}]}}, "ttcc:0": {"name": "ttcc:0", "dtype": "DT_FLOAT", "tensorShape": {"dim": [{"size": "-1"}]}}, "gcgc:0": {"name": "gcgc:0", "dtype": "DT_FLOAT", "tensorShape": {"dim": [{"size": "-1"}]}}, "ttaa:0": {"name": "ttaa:0", "dtype": "DT_FLOAT", "tensorShape": {"dim": [{"size": "-1"}]}}, "gcat:0": {"name": "gcat:0", "dtype": "DT_FLOAT", "tensorShape": {"dim": [{"size": "-1"}]}}, "atgc:0": {"name": "atgc:0", "dtype": "DT_FLOAT", "tensorShape": {"dim": [{"size": "-1"}]}}, "atct:0": {"name": "atct:0", "dtype": "DT_FLOAT", "tensorShape": {"dim": [{"size": "-1"}]}}, "ctag:0": {"name": "ctag:0", "dtype": "DT_FLOAT", "tensorShape": {"dim": [{"size": "-1"}]}}, "ccgg:0": {"name": "ccgg:0", "dtype": "DT_FLOAT", "tensorShape": {"dim": [{"size": "-1"}]}}, "ttgt:0": {"name": "ttgt:0", "dtype": "DT_FLOAT", "tensorShape": {"dim": [{"size": "-1"}]}}, "ctcc:0": {"name": "ctcc:0", "dtype": "DT_FLOAT", "tensorShape": {"dim": [{"size": "-1"}]}}, "tctg:0": {"name": "tctg:0", "dtype": "DT_FLOAT", "tensorShape": {"dim": [{"size": "-1"}]}}, "tcgt:0": {"name": "tcgt:0", "dtype": "DT_FLOAT", "tensorShape": {"dim": [{"size": "-1"}]}}, "tcta:0": {"name": "tcta:0", "dtype": "DT_FLOAT", "tensorShape": {"dim": [{"size": "-1"}]}}, "atgt:0": {"name": "atgt:0", "dtype": "DT_FLOAT", "tensorShape": {"dim": [{"size": "-1"}]}}, "gcaa:0": {"name": "gcaa:0", "dtype": "DT_FLOAT", "tensorShape": {"dim": [{"size": "-1"}]}}, "ccac:0": {"name": "ccac:0", "dtype": "DT_FLOAT", "tensorShape": {"dim": [{"size": "-1"}]}}, "ccta:0": {"name": "ccta:0", "dtype": "DT_FLOAT", "tensorShape": {"dim": [{"size": "-1"}]}}, "actg:0": {"name": "actg:0", "dtype": "DT_FLOAT", "tensorShape": {"dim": [{"size": "-1"}]}}, "atcc:0": {"name": "atcc:0", "dtype": "DT_FLOAT", "tensorShape": {"dim": [{"size": "-1"}]}}, "tcag:0": {"name": "tcag:0", "dtype": "DT_FLOAT", "tensorShape": {"dim": [{"size": "-1"}]}}, "gctt:0": {"name": "gctt:0", "dtype": "DT_FLOAT", "tensorShape": {"dim": [{"size": "-1"}]}}, "gcta:0": {"name": "gcta:0", "dtype": "DT_FLOAT", "tensorShape": {"dim": [{"size": "-1"}]}}, "ctat:0": {"name": "ctat:0", "dtype": "DT_FLOAT", "tensorShape": {"dim": [{"size": "-1"}]}}, "ctct:0": {"name": "ctct:0", "dtype": "DT_FLOAT", "tensorShape": {"dim": [{"size": "-1"}]}}, "ttgc:0": {"name": "ttgc:0", "dtype": "DT_FLOAT", "tensorShape": {"dim": [{"size": "-1"}]}}, "tctt:0": {"name": "tctt:0", "dtype": "DT_FLOAT", "tensorShape": {"dim": [{"size": "-1"}]}}, "acaa:0": {"name": "acaa:0", "dtype": "DT_FLOAT", "tensorShape": {"dim": [{"size": "-1"}]}}, "gtac:0": {"name": "gtac:0", "dtype": "DT_FLOAT", "tensorShape": {"dim": [{"size": "-1"}]}}, "atca:0": {"name": "atca:0", "dtype": "DT_FLOAT", "tensorShape": {"dim": [{"size": "-1"}]}}, "ccga:0": {"name": "ccga:0", "dtype": "DT_FLOAT", "tensorShape": {"dim": [{"size": "-1"}]}}, "ccaa:0": {"name": "ccaa:0", "dtype": "DT_FLOAT", "tensorShape": {"dim": [{"size": "-1"}]}}, "ccgt:0": {"name": "ccgt:0", "dtype": "DT_FLOAT", "tensorShape": {"dim": [{"size": "-1"}]}}, "ctgg:0": {"name": "ctgg:0", "dtype": "DT_FLOAT", "tensorShape": {"dim": [{"size": "-1"}]}}, "ctgt:0": {"name": "ctgt:0", "dtype": "DT_FLOAT", "tensorShape": {"dim": [{"size": "-1"}]}}, "ataa:0": {"name": "ataa:0", "dtype": "DT_FLOAT", "tensorShape": {"dim": [{"size": "-1"}]}}, "gcag:0": {"name": "gcag:0", "dtype": "DT_FLOAT", "tensorShape": {"dim": [{"size": "-1"}]}}, "tcgg:0": {"name": "tcgg:0", "dtype": "DT_FLOAT", "tensorShape": {"dim": [{"size": "-1"}]}}, "gtgg:0": {"name": "gtgg:0", "dtype": "DT_FLOAT", "tensorShape": {"dim": [{"size": "-1"}]}}, "acat:0": {"name": "acat:0", "dtype": "DT_FLOAT", "tensorShape": {"dim": [{"size": "-1"}]}}, "ctac:0": {"name": "ctac:0", "dtype": "DT_FLOAT", "tensorShape": {"dim": [{"size": "-1"}]}}, "gtgt:0": {"name": "gtgt:0", "dtype": "DT_FLOAT", "tensorShape": {"dim": [{"size": "-1"}]}}, "ctcg:0": {"name": "ctcg:0", "dtype": "DT_FLOAT", "tensorShape": {"dim": [{"size": "-1"}]}}, "gctg:0": {"name": "gctg:0", "dtype": "DT_FLOAT", "tensorShape": {"dim": [{"size": "-1"}]}}, "tcgc:0": {"name": "tcgc:0", "dtype": "DT_FLOAT", "tensorShape": {"dim": [{"size": "-1"}]}}, "cctc:0": {"name": "cctc:0", "dtype": "DT_FLOAT", "tensorShape": {"dim": [{"size": "-1"}]}}, "gtcg:0": {"name": "gtcg:0", "dtype": "DT_FLOAT", "tensorShape": {"dim": [{"size": "-1"}]}}, "acac:0": {"name": "acac:0", "dtype": "DT_FLOAT", "tensorShape": {"dim": [{"size": "-1"}]}}, "tcga:0": {"name": "tcga:0", "dtype": "DT_FLOAT", "tensorShape": {"dim": [{"size": "-1"}]}}, "acgc:0": {"name": "acgc:0", "dtype": "DT_FLOAT", "tensorShape": {"dim": [{"size": "-1"}]}}, "cctg:0": {"name": "cctg:0", "dtype": "DT_FLOAT", "tensorShape": {"dim": [{"size": "-1"}]}}, "atga:0": {"name": "atga:0", "dtype": "DT_FLOAT", "tensorShape": {"dim": [{"size": "-1"}]}}, "ccat:0": {"name": "ccat:0", "dtype": "DT_FLOAT", "tensorShape": {"dim": [{"size": "-1"}]}}, "atat:0": {"name": "atat:0", "dtype": "DT_FLOAT", "tensorShape": {"dim": [{"size": "-1"}]}}, "cctt:0": {"name": "cctt:0", "dtype": "DT_FLOAT", "tensorShape": {"dim": [{"size": "-1"}]}}, "gcac:0": {"name": "gcac:0", "dtype": "DT_FLOAT", "tensorShape": {"dim": [{"size": "-1"}]}}, "atag:0": {"name": "atag:0", "dtype": "DT_FLOAT", "tensorShape": {"dim": [{"size": "-1"}]}}}, "outputs": {"output_1": {"name": "Identity:0", "dtype": "DT_FLOAT", "tensorShape": {"dim": [{"size": "-1"}, {"size": "1"}]}}}}, "modelTopology": {"node": [{"name": "acaa", "op": "Placeholder", "attr": {"dtype": {"type": "DT_FLOAT"}, "shape": {"shape": {"dim": [{"size": "-1"}]}}}}, {"name": "acac", "op": "Placeholder", "attr": {"shape": {"shape": {"dim": [{"size": "-1"}]}}, "dtype": {"type": "DT_FLOAT"}}}, {"name": "acag", "op": "Placeholder", "attr": {"dtype": {"type": "DT_FLOAT"}, "shape": {"shape": {"dim": [{"size": "-1"}]}}}}, {"name": "acat", "op": "Placeholder", "attr": {"dtype": {"type": "DT_FLOAT"}, "shape": {"shape": {"dim": [{"size": "-1"}]}}}}, {"name": "acga", "op": "Placeholder", "attr": {"shape": {"shape": {"dim": [{"size": "-1"}]}}, "dtype": {"type": "DT_FLOAT"}}}, {"name": "acgc", "op": "Placeholder", "attr": {"shape": {"shape": {"dim": [{"size": "-1"}]}}, "dtype": {"type": "DT_FLOAT"}}}, {"name": "acgg", "op": "Placeholder", "attr": {"shape": {"shape": {"dim": [{"size": "-1"}]}}, "dtype": {"type": "DT_FLOAT"}}}, {"name": "acgt", "op": "Placeholder", "attr": {"dtype": {"type": "DT_FLOAT"}, "shape": {"shape": {"dim": [{"size": "-1"}]}}}}, {"name": "acta", "op": "Placeholder", "attr": {"dtype": {"type": "DT_FLOAT"}, "shape": {"shape": {"dim": [{"size": "-1"}]}}}}, {"name": "actc", "op": "Placeholder", "attr": {"shape": {"shape": {"dim": [{"size": "-1"}]}}, "dtype": {"type": "DT_FLOAT"}}}, {"name": "actg", "op": "Placeholder", "attr": {"dtype": {"type": "DT_FLOAT"}, "shape": {"shape": {"dim": [{"size": "-1"}]}}}}, {"name": "actt", "op": "Placeholder", "attr": {"shape": {"shape": {"dim": [{"size": "-1"}]}}, "dtype": {"type": "DT_FLOAT"}}}, {"name": "ataa", "op": "Placeholder", "attr": {"dtype": {"type": "DT_FLOAT"}, "shape": {"shape": {"dim": [{"size": "-1"}]}}}}, {"name": "atac", "op": "Placeholder", "attr": {"shape": {"shape": {"dim": [{"size": "-1"}]}}, "dtype": {"type": "DT_FLOAT"}}}, {"name": "atag", "op": "Placeholder", "attr": {"shape": {"shape": {"dim": [{"size": "-1"}]}}, "dtype": {"type": "DT_FLOAT"}}}, {"name": "atat", "op": "Placeholder", "attr": {"dtype": {"type": "DT_FLOAT"}, "shape": {"shape": {"dim": [{"size": "-1"}]}}}}, {"name": "atca", "op": "Placeholder", "attr": {"shape": {"shape": {"dim": [{"size": "-1"}]}}, "dtype": {"type": "DT_FLOAT"}}}, {"name": "atcc", "op": "Placeholder", "attr": {"dtype": {"type": "DT_FLOAT"}, "shape": {"shape": {"dim": [{"size": "-1"}]}}}}, {"name": "atcg", "op": "Placeholder", "attr": {"shape": {"shape": {"dim": [{"size": "-1"}]}}, "dtype": {"type": "DT_FLOAT"}}}, {"name": "atct", "op": "Placeholder", "attr": {"dtype": {"type": "DT_FLOAT"}, "shape": {"shape": {"dim": [{"size": "-1"}]}}}}, {"name": "atga", "op": "Placeholder", "attr": {"dtype": {"type": "DT_FLOAT"}, "shape": {"shape": {"dim": [{"size": "-1"}]}}}}, {"name": "atgc", "op": "Placeholder", "attr": {"shape": {"shape": {"dim": [{"size": "-1"}]}}, "dtype": {"type": "DT_FLOAT"}}}, {"name": "atgg", "op": "Placeholder", "attr": {"shape": {"shape": {"dim": [{"size": "-1"}]}}, "dtype": {"type": "DT_FLOAT"}}}, {"name": "atgt", "op": "Placeholder", "attr": {"shape": {"shape": {"dim": [{"size": "-1"}]}}, "dtype": {"type": "DT_FLOAT"}}}, {"name": "ccaa", "op": "Placeholder", "attr": {"shape": {"shape": {"dim": [{"size": "-1"}]}}, "dtype": {"type": "DT_FLOAT"}}}, {"name": "ccac", "op": "Placeholder", "attr": {"shape": {"shape": {"dim": [{"size": "-1"}]}}, "dtype": {"type": "DT_FLOAT"}}}, {"name": "ccag", "op": "Placeholder", "attr": {"dtype": {"type": "DT_FLOAT"}, "shape": {"shape": {"dim": [{"size": "-1"}]}}}}, {"name": "ccat", "op": "Placeholder", "attr": {"dtype": {"type": "DT_FLOAT"}, "shape": {"shape": {"dim": [{"size": "-1"}]}}}}, {"name": "ccga", "op": "Placeholder", "attr": {"shape": {"shape": {"dim": [{"size": "-1"}]}}, "dtype": {"type": "DT_FLOAT"}}}, {"name": "ccgc", "op": "Placeholder", "attr": {"shape": {"shape": {"dim": [{"size": "-1"}]}}, "dtype": {"type": "DT_FLOAT"}}}, {"name": "ccgg", "op": "Placeholder", "attr": {"dtype": {"type": "DT_FLOAT"}, "shape": {"shape": {"dim": [{"size": "-1"}]}}}}, {"name": "ccgt", "op": "Placeholder", "attr": {"dtype": {"type": "DT_FLOAT"}, "shape": {"shape": {"dim": [{"size": "-1"}]}}}}, {"name": "ccta", "op": "Placeholder", "attr": {"dtype": {"type": "DT_FLOAT"}, "shape": {"shape": {"dim": [{"size": "-1"}]}}}}, {"name": "cctc", "op": "Placeholder", "attr": {"shape": {"shape": {"dim": [{"size": "-1"}]}}, "dtype": {"type": "DT_FLOAT"}}}, {"name": "cctg", "op": "Placeholder", "attr": {"shape": {"shape": {"dim": [{"size": "-1"}]}}, "dtype": {"type": "DT_FLOAT"}}}, {"name": "cctt", "op": "Placeholder", "attr": {"dtype": {"type": "DT_FLOAT"}, "shape": {"shape": {"dim": [{"size": "-1"}]}}}}, {"name": "ctaa", "op": "Placeholder", "attr": {"dtype": {"type": "DT_FLOAT"}, "shape": {"shape": {"dim": [{"size": "-1"}]}}}}, {"name": "ctac", "op": "Placeholder", "attr": {"dtype": {"type": "DT_FLOAT"}, "shape": {"shape": {"dim": [{"size": "-1"}]}}}}, {"name": "ctag", "op": "Placeholder", "attr": {"shape": {"shape": {"dim": [{"size": "-1"}]}}, "dtype": {"type": "DT_FLOAT"}}}, {"name": "ctat", "op": "Placeholder", "attr": {"dtype": {"type": "DT_FLOAT"}, "shape": {"shape": {"dim": [{"size": "-1"}]}}}}, {"name": "ctca", "op": "Placeholder", "attr": {"shape": {"shape": {"dim": [{"size": "-1"}]}}, "dtype": {"type": "DT_FLOAT"}}}, {"name": "ctcc", "op": "Placeholder", "attr": {"dtype": {"type": "DT_FLOAT"}, "shape": {"shape": {"dim": [{"size": "-1"}]}}}}, {"name": "ctcg", "op": "Placeholder", "attr": {"shape": {"shape": {"dim": [{"size": "-1"}]}}, "dtype": {"type": "DT_FLOAT"}}}, {"name": "ctct", "op": "Placeholder", "attr": {"dtype": {"type": "DT_FLOAT"}, "shape": {"shape": {"dim": [{"size": "-1"}]}}}}, {"name": "ctga", "op": "Placeholder", "attr": {"shape": {"shape": {"dim": [{"size": "-1"}]}}, "dtype": {"type": "DT_FLOAT"}}}, {"name": "ctgc", "op": "Placeholder", "attr": {"shape": {"shape": {"dim": [{"size": "-1"}]}}, "dtype": {"type": "DT_FLOAT"}}}, {"name": "ctgg", "op": "Placeholder", "attr": {"dtype": {"type": "DT_FLOAT"}, "shape": {"shape": {"dim": [{"size": "-1"}]}}}}, {"name": "ctgt", "op": "Placeholder", "attr": {"dtype": {"type": "DT_FLOAT"}, "shape": {"shape": {"dim": [{"size": "-1"}]}}}}, {"name": "gcaa", "op": "Placeholder", "attr": {"shape": {"shape": {"dim": [{"size": "-1"}]}}, "dtype": {"type": "DT_FLOAT"}}}, {"name": "gcac", "op": "Placeholder", "attr": {"dtype": {"type": "DT_FLOAT"}, "shape": {"shape": {"dim": [{"size": "-1"}]}}}}, {"name": "gcag", "op": "Placeholder", "attr": {"dtype": {"type": "DT_FLOAT"}, "shape": {"shape": {"dim": [{"size": "-1"}]}}}}, {"name": "gcat", "op": "Placeholder", "attr": {"dtype": {"type": "DT_FLOAT"}, "shape": {"shape": {"dim": [{"size": "-1"}]}}}}, {"name": "gcga", "op": "Placeholder", "attr": {"shape": {"shape": {"dim": [{"size": "-1"}]}}, "dtype": {"type": "DT_FLOAT"}}}, {"name": "gcgc", "op": "Placeholder", "attr": {"shape": {"shape": {"dim": [{"size": "-1"}]}}, "dtype": {"type": "DT_FLOAT"}}}, {"name": "gcgg", "op": "Placeholder", "attr": {"shape": {"shape": {"dim": [{"size": "-1"}]}}, "dtype": {"type": "DT_FLOAT"}}}, {"name": "gcgt", "op": "Placeholder", "attr": {"shape": {"shape": {"dim": [{"size": "-1"}]}}, "dtype": {"type": "DT_FLOAT"}}}, {"name": "gcta", "op": "Placeholder", "attr": {"dtype": {"type": "DT_FLOAT"}, "shape": {"shape": {"dim": [{"size": "-1"}]}}}}, {"name": "gctc", "op": "Placeholder", "attr": {"dtype": {"type": "DT_FLOAT"}, "shape": {"shape": {"dim": [{"size": "-1"}]}}}}, {"name": "gctg", "op": "Placeholder", "attr": {"shape": {"shape": {"dim": [{"size": "-1"}]}}, "dtype": {"type": "DT_FLOAT"}}}, {"name": "gctt", "op": "Placeholder", "attr": {"shape": {"shape": {"dim": [{"size": "-1"}]}}, "dtype": {"type": "DT_FLOAT"}}}, {"name": "gtaa", "op": "Placeholder", "attr": {"dtype": {"type": "DT_FLOAT"}, "shape": {"shape": {"dim": [{"size": "-1"}]}}}}, {"name": "gtac", "op": "Placeholder", "attr": {"dtype": {"type": "DT_FLOAT"}, "shape": {"shape": {"dim": [{"size": "-1"}]}}}}, {"name": "gtag", "op": "Placeholder", "attr": {"dtype": {"type": "DT_FLOAT"}, "shape": {"shape": {"dim": [{"size": "-1"}]}}}}, {"name": "gtat", "op": "Placeholder", "attr": {"shape": {"shape": {"dim": [{"size": "-1"}]}}, "dtype": {"type": "DT_FLOAT"}}}, {"name": "gtca", "op": "Placeholder", "attr": {"dtype": {"type": "DT_FLOAT"}, "shape": {"shape": {"dim": [{"size": "-1"}]}}}}, {"name": "gtcc", "op": "Placeholder", "attr": {"shape": {"shape": {"dim": [{"size": "-1"}]}}, "dtype": {"type": "DT_FLOAT"}}}, {"name": "gtcg", "op": "Placeholder", "attr": {"shape": {"shape": {"dim": [{"size": "-1"}]}}, "dtype": {"type": "DT_FLOAT"}}}, {"name": "gtct", "op": "Placeholder", "attr": {"shape": {"shape": {"dim": [{"size": "-1"}]}}, "dtype": {"type": "DT_FLOAT"}}}, {"name": "gtga", "op": "Placeholder", "attr": {"dtype": {"type": "DT_FLOAT"}, "shape": {"shape": {"dim": [{"size": "-1"}]}}}}, {"name": "gtgc", "op": "Placeholder", "attr": {"shape": {"shape": {"dim": [{"size": "-1"}]}}, "dtype": {"type": "DT_FLOAT"}}}, {"name": "gtgg", "op": "Placeholder", "attr": {"dtype": {"type": "DT_FLOAT"}, "shape": {"shape": {"dim": [{"size": "-1"}]}}}}, {"name": "gtgt", "op": "Placeholder", "attr": {"dtype": {"type": "DT_FLOAT"}, "shape": {"shape": {"dim": [{"size": "-1"}]}}}}, {"name": "tcaa", "op": "Placeholder", "attr": {"shape": {"shape": {"dim": [{"size": "-1"}]}}, "dtype": {"type": "DT_FLOAT"}}}, {"name": "tcac", "op": "Placeholder", "attr": {"shape": {"shape": {"dim": [{"size": "-1"}]}}, "dtype": {"type": "DT_FLOAT"}}}, {"name": "tcag", "op": "Placeholder", "attr": {"shape": {"shape": {"dim": [{"size": "-1"}]}}, "dtype": {"type": "DT_FLOAT"}}}, {"name": "tcat", "op": "Placeholder", "attr": {"dtype": {"type": "DT_FLOAT"}, "shape": {"shape": {"dim": [{"size": "-1"}]}}}}, {"name": "tcga", "op": "Placeholder", "attr": {"dtype": {"type": "DT_FLOAT"}, "shape": {"shape": {"dim": [{"size": "-1"}]}}}}, {"name": "tcgc", "op": "Placeholder", "attr": {"shape": {"shape": {"dim": [{"size": "-1"}]}}, "dtype": {"type": "DT_FLOAT"}}}, {"name": "tcgg", "op": "Placeholder", "attr": {"dtype": {"type": "DT_FLOAT"}, "shape": {"shape": {"dim": [{"size": "-1"}]}}}}, {"name": "tcgt", "op": "Placeholder", "attr": {"dtype": {"type": "DT_FLOAT"}, "shape": {"shape": {"dim": [{"size": "-1"}]}}}}, {"name": "tcta", "op": "Placeholder", "attr": {"dtype": {"type": "DT_FLOAT"}, "shape": {"shape": {"dim": [{"size": "-1"}]}}}}, {"name": "tctc", "op": "Placeholder", "attr": {"dtype": {"type": "DT_FLOAT"}, "shape": {"shape": {"dim": [{"size": "-1"}]}}}}, {"name": "tctg", "op": "Placeholder", "attr": {"shape": {"shape": {"dim": [{"size": "-1"}]}}, "dtype": {"type": "DT_FLOAT"}}}, {"name": "tctt", "op": "Placeholder", "attr": {"shape": {"shape": {"dim": [{"size": "-1"}]}}, "dtype": {"type": "DT_FLOAT"}}}, {"name": "ttaa", "op": "Placeholder", "attr": {"shape": {"shape": {"dim": [{"size": "-1"}]}}, "dtype": {"type": "DT_FLOAT"}}}, {"name": "ttac", "op": "Placeholder", "attr": {"dtype": {"type": "DT_FLOAT"}, "shape": {"shape": {"dim": [{"size": "-1"}]}}}}, {"name": "ttag", "op": "Placeholder", "attr": {"shape": {"shape": {"dim": [{"size": "-1"}]}}, "dtype": {"type": "DT_FLOAT"}}}, {"name": "ttat", "op": "Placeholder", "attr": {"dtype": {"type": "DT_FLOAT"}, "shape": {"shape": {"dim": [{"size": "-1"}]}}}}, {"name": "ttca", "op": "Placeholder", "attr": {"dtype": {"type": "DT_FLOAT"}, "shape": {"shape": {"dim": [{"size": "-1"}]}}}}, {"name": "ttcc", "op": "Placeholder", "attr": {"dtype": {"type": "DT_FLOAT"}, "shape": {"shape": {"dim": [{"size": "-1"}]}}}}, {"name": "ttcg", "op": "Placeholder", "attr": {"dtype": {"type": "DT_FLOAT"}, "shape": {"shape": {"dim": [{"size": "-1"}]}}}}, {"name": "ttct", "op": "Placeholder", "attr": {"shape": {"shape": {"dim": [{"size": "-1"}]}}, "dtype": {"type": "DT_FLOAT"}}}, {"name": "ttga", "op": "Placeholder", "attr": {"dtype": {"type": "DT_FLOAT"}, "shape": {"shape": {"dim": [{"size": "-1"}]}}}}, {"name": "ttgc", "op": "Placeholder", "attr": {"shape": {"shape": {"dim": [{"size": "-1"}]}}, "dtype": {"type": "DT_FLOAT"}}}, {"name": "ttgg", "op": "Placeholder", "attr": {"shape": {"shape": {"dim": [{"size": "-1"}]}}, "dtype": {"type": "DT_FLOAT"}}}, {"name": "ttgt", "op": "Placeholder", "attr": {"shape": {"shape": {"dim": [{"size": "-1"}]}}, "dtype": {"type": "DT_FLOAT"}}}, {"name": "unknown", "op": "Placeholder", "attr": {"shape": {"shape": {}}, "dtype": {"type": "DT_RESOURCE"}}}, {"name": "Func/StatefulPartitionedCall/gradient_boosted_trees_model_4/StatefulPartitionedCall/input_control_node/_99", "op": "NoOp", "input": ["^acaa", "^acac", "^actg", "^actt", "^ataa", "^atac", "^atag", "^atat", "^atca", "^atcc", "^atcg", "^atct", "^acag", "^atga", "^atgc", "^atgg", "^atgt", "^ccaa", "^ccac", "^ccag", "^ccat", "^ccga", "^ccgc", "^acat", "^ccgg", "^ccgt", "^ccta", "^cctc", "^cctg", "^cctt", "^ctaa", "^ctac", "^ctag", "^ctat", "^acga", "^ctca", "^ctcc", "^ctcg", "^ctct", "^ctga", "^ctgc", "^ctgg", "^ctgt", "^gcaa", "^gcac", "^acgc", "^gcag", "^gcat", "^gcga", "^gcgc", "^gcgg", "^gcgt", "^gcta", "^gctc", "^gctg", "^gctt", "^acgg", "^gtaa", "^gtac", "^gtag", "^gtat", "^gtca", "^gtcc", "^gtcg", "^gtct", "^gtga", "^gtgc", "^acgt", "^gtgg", "^gtgt", "^tcaa", "^tcac", "^tcag", "^tcat", "^tcga", "^tcgc", "^tcgg", "^tcgt", "^acta", "^tcta", "^tctc", "^tctg", "^tctt", "^ttaa", "^ttac", "^ttag", "^ttat", "^ttca", "^ttcc", "^actc", "^ttcg", "^ttct", "^ttga", "^ttgc", "^ttgg", "^ttgt", "^unknown"], "attr": {"_has_manual_control_dependencies": {"b": true}}}, {"name": "StatefulPartitionedCall/gradient_boosted_trees_model_4/StatefulPartitionedCall/stack", "op": "Pack", "input": ["acaa", "acac", "acag", "acat", "acga", "acgc", "acgg", "acgt", "acta", "actc", "actg", "actt", "ataa", "atac", "atag", "atat", "atca", "atcc", "atcg", "atct", "atga", "atgc", "atgg", "atgt", "ccaa", "ccac", "ccag", "ccat", "ccga", "ccgc", "ccgg", "ccgt", "ccta", "cctc", "cctg", "cctt", "ctaa", "ctac", "ctag", "ctat", "ctca", "ctcc", "ctcg", "ctct", "ctga", "ctgc", "ctgg", "ctgt", "gcaa", "gcac", "gcag", "gcat", "gcga", "gcgc", "gcgg", "gcgt", "gcta", "gctc", "gctg", "gctt", "gtaa", "gtac", "gtag", "gtat", "gtca", "gtcc", "gtcg", "gtct", "gtga", "gtgc", "gtgg", "gtgt", "tcaa", "tcac", "tcag", "tcat", "tcga", "tcgc", "tcgg", "tcgt", "tcta", "tctc", "tctg", "tctt", "ttaa", "ttac", "ttag", "ttat", "ttca", "ttcc", "ttcg", "ttct", "ttga", "ttgc", "ttgg", "ttgt", "^Func/StatefulPartitionedCall/gradient_boosted_trees_model_4/StatefulPartitionedCall/input_control_node/_99"], "attr": {"axis": {"i": "1"}, "T": {"type": "DT_FLOAT"}, "N": {"i": "96"}}}, {"name": "StatefulPartitionedCall/gradient_boosted_trees_model_4/StatefulPartitionedCall/Const", "op": "Const", "input": ["^Func/StatefulPartitionedCall/gradient_boosted_trees_model_4/StatefulPartitionedCall/input_control_node/_99"], "attr": {"dtype": {"type": "DT_FLOAT"}, "value": {"tensor": {"dtype": "DT_FLOAT", "tensorShape": {"dim": [{}, {}]}}}}}, {"name": "StatefulPartitionedCall/gradient_boosted_trees_model_4/StatefulPartitionedCall/Const_1", "op": "Const", "input": ["^Func/StatefulPartitionedCall/gradient_boosted_trees_model_4/StatefulPartitionedCall/input_control_node/_99"], "attr": {"value": {"tensor": {"dtype": "DT_INT32", "tensorShape": {"dim": [{}, {}]}}}, "dtype": {"type": "DT_INT32"}}}, {"name": "StatefulPartitionedCall/gradient_boosted_trees_model_4/StatefulPartitionedCall/RaggedConstant/values", "op": "Const", "input": ["^Func/StatefulPartitionedCall/gradient_boosted_trees_model_4/StatefulPartitionedCall/input_control_node/_99"], "attr": {"value": {"tensor": {"dtype": "DT_INT32", "tensorShape": {"dim": [{}]}}}, "dtype": {"type": "DT_INT32"}}}, {"name": "StatefulPartitionedCall/gradient_boosted_trees_model_4/StatefulPartitionedCall/RaggedConstant/Const", "op": "Const", "input": ["^Func/StatefulPartitionedCall/gradient_boosted_trees_model_4/StatefulPartitionedCall/input_control_node/_99"], "attr": {"value": {"tensor": {"dtype": "DT_INT64", "tensorShape": {"dim": [{"size": "1"}]}}}, "dtype": {"type": "DT_INT64"}}}, {"name": "StatefulPartitionedCall/gradient_boosted_trees_model_4/StatefulPartitionedCall/RaggedConstant/Const_1", "op": "Const", "input": ["^Func/StatefulPartitionedCall/gradient_boosted_trees_model_4/StatefulPartitionedCall/input_control_node/_99"], "attr": {"dtype": {"type": "DT_INT64"}, "value": {"tensor": {"dtype": "DT_INT64", "tensorShape": {"dim": [{"size": "1"}]}}}}}, {"name": "StatefulPartitionedCall/gradient_boosted_trees_model_4/StatefulPartitionedCall/PartitionedCall_1/strided_slice/stack", "op": "Const", "input": ["^Func/StatefulPartitionedCall/gradient_boosted_trees_model_4/StatefulPartitionedCall/input_control_node/_99"], "attr": {"value": {"tensor": {"dtype": "DT_INT32", "tensorShape": {"dim": [{"size": "2"}]}}}, "dtype": {"type": "DT_INT32"}}}, {"name": "StatefulPartitionedCall/gradient_boosted_trees_model_4/StatefulPartitionedCall/PartitionedCall_1/strided_slice/stack_1", "op": "Const", "input": ["^Func/StatefulPartitionedCall/gradient_boosted_trees_model_4/StatefulPartitionedCall/input_control_node/_99"], "attr": {"dtype": {"type": "DT_INT32"}, "value": {"tensor": {"dtype": "DT_INT32", "tensorShape": {"dim": [{"size": "2"}]}}}}}, {"name": "StatefulPartitionedCall/gradient_boosted_trees_model_4/StatefulPartitionedCall/PartitionedCall_1/strided_slice/stack_2", "op": "Const", "input": ["^Func/StatefulPartitionedCall/gradient_boosted_trees_model_4/StatefulPartitionedCall/input_control_node/_99"], "attr": {"dtype": {"type": "DT_INT32"}, "value": {"tensor": {"dtype": "DT_INT32", "tensorShape": {"dim": [{"size": "2"}]}}}}}, {"name": "StatefulPartitionedCall/gradient_boosted_trees_model_4/StatefulPartitionedCall/inference_op", "op": "SimpleMLInferenceOpWithHandle", "input": ["StatefulPartitionedCall/gradient_boosted_trees_model_4/StatefulPartitionedCall/stack", "StatefulPartitionedCall/gradient_boosted_trees_model_4/StatefulPartitionedCall/Const", "StatefulPartitionedCall/gradient_boosted_trees_model_4/StatefulPartitionedCall/Const_1", "StatefulPartitionedCall/gradient_boosted_trees_model_4/StatefulPartitionedCall/RaggedConstant/values", "StatefulPartitionedCall/gradient_boosted_trees_model_4/StatefulPartitionedCall/RaggedConstant/Const", "StatefulPartitionedCall/gradient_boosted_trees_model_4/StatefulPartitionedCall/RaggedConstant/Const_1", "unknown"], "attr": {"dense_output_dim": {"i": "2"}, "_has_manual_control_dependencies": {"b": true}}}, {"name": "StatefulPartitionedCall/gradient_boosted_trees_model_4/StatefulPartitionedCall/PartitionedCall_1/strided_slice", "op": "StridedSlice", "input": ["StatefulPartitionedCall/gradient_boosted_trees_model_4/StatefulPartitionedCall/inference_op", "StatefulPartitionedCall/gradient_boosted_trees_model_4/StatefulPartitionedCall/PartitionedCall_1/strided_slice/stack", "StatefulPartitionedCall/gradient_boosted_trees_model_4/StatefulPartitionedCall/PartitionedCall_1/strided_slice/stack_1", "StatefulPartitionedCall/gradient_boosted_trees_model_4/StatefulPartitionedCall/PartitionedCall_1/strided_slice/stack_2"], "attr": {"shrink_axis_mask": {"i": "0"}, "end_mask": {"i": "1"}, "new_axis_mask": {"i": "0"}, "ellipsis_mask": {"i": "0"}, "Index": {"type": "DT_INT32"}, "begin_mask": {"i": "1"}, "T": {"type": "DT_FLOAT"}}}, {"name": "Identity", "op": "Identity", "input": ["StatefulPartitionedCall/gradient_boosted_trees_model_4/StatefulPartitionedCall/PartitionedCall_1/strided_slice"], "attr": {"T": {"type": "DT_FLOAT"}}}], "library": {}, "versions": {"producer": 1286}}, "modelInitializer": {"node": [{"name": "Func/StatefulPartitionedCall/input_control_node/_0", "op": "NoOp", "attr": {"_has_manual_control_dependencies": {"b": true}}}, {"name": "3989", "op": "Const", "attr": {"value": {"tensor": {"dtype": "DT_STRING", "tensorShape": {}}}, "_has_manual_control_dependencies": {"b": true}, "dtype": {"type": "DT_STRING"}}}, {"name": "Func/StatefulPartitionedCall/StatefulPartitionedCall/input_control_node/_8", "op": "NoOp", "input": ["^Func/StatefulPartitionedCall/input_control_node/_0"], "attr": {"_has_manual_control_dependencies": {"b": true}}}, {"name": "StatefulPartitionedCall/StatefulPartitionedCall/SimpleMLCreateModelResource", "op": "SimpleMLCreateModelResource", "input": ["^Func/StatefulPartitionedCall/StatefulPartitionedCall/input_control_node/_8"], "attr": {"_has_manual_control_dependencies": {"b": true}, "container": {"s": ""}, "shared_name": {"s": "c2ltcGxlX21sX21vZGVsXzY4OGVkYTQxLTVmMWItNDQ2MS1iZGNiLTVjNDE1MTRjMTNlOF9sb2FkXzE="}}}, {"name": "Func/StatefulPartitionedCall/StatefulPartitionedCall/output_control_node/_10", "op": "NoOp", "input": ["^StatefulPartitionedCall/StatefulPartitionedCall/SimpleMLCreateModelResource"], "attr": {"_has_manual_control_dependencies": {"b": true}}}, {"name": "Func/StatefulPartitionedCall/output_control_node/_2", "op": "NoOp", "input": ["^Func/StatefulPartitionedCall/StatefulPartitionedCall/output_control_node/_10"], "attr": {"_has_manual_control_dependencies": {"b": true}}}, {"name": "StatefulPartitionedCall/StatefulPartitionedCall/NoOp", "op": "NoOp", "input": ["^StatefulPartitionedCall/StatefulPartitionedCall/SimpleMLCreateModelResource"], "attr": {"_has_manual_control_dependencies": {"b": true}, "_acd_function_control_output": {"b": true}}}, {"name": "StatefulPartitionedCall/StatefulPartitionedCall/Identity", "op": "Identity", "input": ["StatefulPartitionedCall/StatefulPartitionedCall/SimpleMLCreateModelResource", "^StatefulPartitionedCall/StatefulPartitionedCall/NoOp"], "attr": {"T": {"type": "DT_RESOURCE"}}}, {"name": "Func/StatefulPartitionedCall/StatefulPartitionedCall/output/_9", "op": "Identity", "input": ["StatefulPartitionedCall/StatefulPartitionedCall/Identity"], "attr": {"T": {"type": "DT_RESOURCE"}}}, {"name": "StatefulPartitionedCall/NoOp", "op": "NoOp", "input": ["^Func/StatefulPartitionedCall/StatefulPartitionedCall/output_control_node/_10"], "attr": {"_has_manual_control_dependencies": {"b": true}, "_acd_function_control_output": {"b": true}}}, {"name": "StatefulPartitionedCall/Identity", "op": "Identity", "input": ["Func/StatefulPartitionedCall/StatefulPartitionedCall/output/_9", "^StatefulPartitionedCall/NoOp"], "attr": {"T": {"type": "DT_RESOURCE"}}}, {"name": "Func/StatefulPartitionedCall/output/_1", "op": "Identity", "input": ["StatefulPartitionedCall/Identity"], "attr": {"T": {"type": "DT_RESOURCE"}, "_has_manual_control_dependencies": {"b": true}}}, {"name": "Func/StatefulPartitionedCall_1/input_control_node/_3", "op": "NoOp", "input": ["^3989", "^Func/StatefulPartitionedCall/output/_1"], "attr": {"_has_manual_control_dependencies": {"b": true}}}, {"name": "Func/StatefulPartitionedCall_1/input/_5", "op": "Identity", "input": ["Func/StatefulPartitionedCall/output/_1", "^Func/StatefulPartitionedCall_1/input_control_node/_3"], "attr": {"T": {"type": "DT_RESOURCE"}}}, {"name": "Func/StatefulPartitionedCall_1/StatefulPartitionedCall/input_control_node/_11", "op": "NoOp", "input": ["^Func/StatefulPartitionedCall_1/input_control_node/_3"], "attr": {"_has_manual_control_dependencies": {"b": true}}}, {"name": "Func/StatefulPartitionedCall_1/StatefulPartitionedCall/input/_13", "op": "Identity", "input": ["Func/StatefulPartitionedCall_1/input/_5", "^Func/StatefulPartitionedCall_1/StatefulPartitionedCall/input_control_node/_11"], "attr": {"T": {"type": "DT_RESOURCE"}}}, {"name": "Func/StatefulPartitionedCall_1/input/_4", "op": "Identity", "input": ["3989", "^Func/StatefulPartitionedCall_1/input_control_node/_3"], "attr": {"T": {"type": "DT_STRING"}}}, {"name": "Func/StatefulPartitionedCall_1/StatefulPartitionedCall/input/_12", "op": "Identity", "input": ["Func/StatefulPartitionedCall_1/input/_4", "^Func/StatefulPartitionedCall_1/StatefulPartitionedCall/input_control_node/_11"], "attr": {"T": {"type": "DT_STRING"}}}, {"name": "StatefulPartitionedCall_1/StatefulPartitionedCall/StaticRegexReplace", "op": "StaticRegexReplace", "input": ["Func/StatefulPartitionedCall_1/StatefulPartitionedCall/input/_12"], "attr": {"replace_global": {"b": true}, "rewrite": {"s": ""}, "pattern": {"s": "ODkzN2UxZDIxMmViNGVkNGRvbmU="}}}, {"name": "StatefulPartitionedCall_1/StatefulPartitionedCall/simple_ml/SimpleMLLoadModelFromPathWithHandle", "op": "SimpleMLLoadModelFromPathWithHandle", "input": ["Func/StatefulPartitionedCall_1/StatefulPartitionedCall/input/_13", "StatefulPartitionedCall_1/StatefulPartitionedCall/StaticRegexReplace"], "attr": {"allow_slow_inference": {"b": true}, "_has_manual_control_dependencies": {"b": true}, "file_prefix": {"s": "ODkzN2UxZDIxMmViNGVkNA=="}, "output_types": {"list": {}}}}, {"name": "Func/StatefulPartitionedCall_1/StatefulPartitionedCall/output_control_node/_15", "op": "NoOp", "input": ["^StatefulPartitionedCall_1/StatefulPartitionedCall/simple_ml/SimpleMLLoadModelFromPathWithHandle"], "attr": {"_has_manual_control_dependencies": {"b": true}}}, {"name": "Func/StatefulPartitionedCall_1/output_control_node/_7", "op": "NoOp", "input": ["^Func/StatefulPartitionedCall_1/StatefulPartitionedCall/output_control_node/_15"], "attr": {"_has_manual_control_dependencies": {"b": true}}}, {"name": "NoOp", "op": "NoOp", "input": ["^Func/StatefulPartitionedCall/output_control_node/_2", "^Func/StatefulPartitionedCall_1/output_control_node/_7"], "attr": {"_acd_function_control_output": {"b": true}, "_has_manual_control_dependencies": {"b": true}}}, {"name": "Identity", "op": "Identity", "input": ["Func/StatefulPartitionedCall/output/_1", "^Func/StatefulPartitionedCall_1/output_control_node/_7", "^NoOp"], "attr": {"T": {"type": "DT_RESOURCE"}}}], "versions": {"producer": 1286}}, "initializerSignature": {"outputs": {"Identity:0": {"name": "Identity:0", "dtype": "DT_RESOURCE", "tensorShape": {}, "resourceId": 2726}}}, "weightsManifest": [{"paths": ["group1-shard1of1.bin"], "weights": [{"name": "StatefulPartitionedCall/gradient_boosted_trees_model_4/StatefulPartitionedCall/Const", "shape": [0, 0], "dtype": "float32"}, {"name": "StatefulPartitionedCall/gradient_boosted_trees_model_4/StatefulPartitionedCall/Const_1", "shape": [0, 0], "dtype": "int32"}, {"name": "StatefulPartitionedCall/gradient_boosted_trees_model_4/StatefulPartitionedCall/RaggedConstant/values", "shape": [0], "dtype": "int32"}, {"name": "StatefulPartitionedCall/gradient_boosted_trees_model_4/StatefulPartitionedCall/RaggedConstant/Const", "shape": [1], "dtype": "int32"}, {"name": "StatefulPartitionedCall/gradient_boosted_trees_model_4/StatefulPartitionedCall/RaggedConstant/Const_1", "shape": [1], "dtype": "int32"}, {"name": "StatefulPartitionedCall/gradient_boosted_trees_model_4/StatefulPartitionedCall/PartitionedCall_1/strided_slice/stack", "shape": [2], "dtype": "int32"}, {"name": "StatefulPartitionedCall/gradient_boosted_trees_model_4/StatefulPartitionedCall/PartitionedCall_1/strided_slice/stack_1", "shape": [2], "dtype": "int32"}, {"name": "StatefulPartitionedCall/gradient_boosted_trees_model_4/StatefulPartitionedCall/PartitionedCall_1/strided_slice/stack_2", "shape": [2], "dtype": "int32"}, {"name": "3989", "shape": [], "dtype": "string"}]}]}